[
  {
    "id": "1780148490357",
    "title": "ロゴ",
    "body": "C:\\Users\\cqb00\\OneDrive\\デスクトップ\\ブランド用画像\\YUKIGAKIロゴ.png",
    "tags": [],
    "createdAt": "2026-05-30T13:41:30.357Z",
    "updatedAt": "2026-05-30T13:46:16.821Z"
  },
  {
    "id": "1780148513004",
    "title": "ブランド名",
    "body": "雪柿や一平を想定している。\n\n雪柿：\n雪景色の中にオレンジの柿のコントラストが好きで、特に名称も存在しないので造語を作ってみた。\nまだ世間に見つかっていない美しさを提示するようなブランドにしたいという気持ち。\n\n一平：\n両親が私の名前を考える中で、一成以外に選択肢として挙がった\n\n雪柿で仮決定としたが、一平の方がシンプルだし私の\n",
    "tags": [],
    "createdAt": "2026-05-30T13:41:53.004Z",
    "updatedAt": "2026-05-30T13:58:03.908Z"
  },
  {
    "id": "1780149261318",
    "title": "",
    "body": "",
    "tags": [],
    "images": [],
    "createdAt": "2026-05-30T13:54:21.318Z",
    "updatedAt": "2026-05-30T13:54:21.318Z"
  }
]